petal_warehouse-0.1.8.dist-info/METADATA
petal_warehouse-0.1.8.dist-info/WHEEL
petal_warehouse-0.1.8.dist-info/entry_points.txt
petal_warehouse/__init__.py
petal_warehouse/plugin.py
petal_warehouse-0.1.8.dist-info/RECORD
