Metadata-Version: 2.1
Name: petal-warehouse
Version: 0.1.8
Summary: Petal for the warehouse management system (WHMS).
Author-Email: Ahmad Almakhamreh <almakhamrehahmad@gmail.com>
License: MIT
Requires-Python: >=3.10
Requires-Dist: petal-app-manager>=0.1.25
